MANIFEST.in
README.md
setup.py
pyAudGrav/AudioAnalysis.py
pyAudGrav/AudioEvent.py
pyAudGrav/AudioIO.py
pyAudGrav/AudioReconstruct.py
pyAudGrav/Examples.py
pyAudGrav/__init__.py
pyAudGrav.egg-info/PKG-INFO
pyAudGrav.egg-info/SOURCES.txt
pyAudGrav.egg-info/dependency_links.txt
pyAudGrav.egg-info/requires.txt
pyAudGrav.egg-info/top_level.txt
pyAudGrav/audio_files/example1_stimmen.wav
pyAudGrav/audio_files/example2_tones.wav
pyAudGrav/audio_files/example3_potsPans.wav
pyAudGrav/audio_files/example4_pingPong.wav
pyAudGrav/audio_files/example5_hey.wav