Metadata-Version: 2.1
Name: pyAudGrav
Version: 0.1.5
Summary: Algorithmically edit and rearrange audio clips, both in time and space, using the equation of gravity.
Home-page: https://github.com/patrickTumulty/audGrav
Author: Patrick Tumulty
Author-email: ptumulty1@gmail.com
License: UNKNOWN
Platform: UNKNOWN
Classifier: Programming Language :: Python :: 3
Classifier: License :: OSI Approved :: GNU General Public License v3 (GPLv3)
Classifier: Operating System :: OS Independent
Requires-Python: >=3.7.3
